LICENSE.txt
README.md
requirements.txt
setup.cfg
setup.py
__tests__/__init__.py
__tests__/extension_test.py
__tests__/process_test.py
__tests__/sequential_bpmn_engine_test.py
__tests__/diagrams/call_activity.bpmn
__tests__/diagrams/error_boundary_event.bpmn
__tests__/diagrams/exclusive_gateway.bpmn
__tests__/diagrams/exclusive_gateway_with_default.bpmn
__tests__/diagrams/http_task.bpmn
__tests__/diagrams/manual_task.bpmn
__tests__/diagrams/message_intermediate_catch_event.bpmn
__tests__/diagrams/message_intermediate_throw_event.bpmn
__tests__/diagrams/message_start_event.bpmn
__tests__/diagrams/receive_task.bpmn
__tests__/diagrams/script_task.bpmn
__tests__/diagrams/send_task.bpmn
__tests__/diagrams/service_task.bpmn
__tests__/diagrams/signal_intermediate_catch_event.bpmn
__tests__/diagrams/signal_intermediate_throw_event.bpmn
__tests__/diagrams/signal_start_event.bpmn
__tests__/diagrams/user_task.bpmn
__tests__/diagrams/extension/complete_expression.bpmn
__tests__/diagrams/extension/continue_expression.bpmn
__tests__/diagrams/extension/initiate_expression.bpmn
__tests__/event/__init__.py
__tests__/event/sink_event_emitter.py
__tests__/parser/xml_bpmn_parser_test.py
arrow.arrow_bpmn.egg-info/PKG-INFO
arrow.arrow_bpmn.egg-info/SOURCES.txt
arrow.arrow_bpmn.egg-info/dependency_links.txt
arrow.arrow_bpmn.egg-info/requires.txt
arrow.arrow_bpmn.egg-info/top_level.txt
arrow_bpmn/__init__.py
arrow_bpmn/__spi__/__init__.py
arrow_bpmn/__spi__/bpmn_edge.py
arrow_bpmn/__spi__/bpmn_node.py
arrow_bpmn/__spi__/bpmn_visitor.py
arrow_bpmn/__spi__/types.py
arrow_bpmn/__spi__/action/__init__.py
arrow_bpmn/__spi__/action/action.py
arrow_bpmn/__spi__/action/cascade_action.py
arrow_bpmn/__spi__/action/complete_action.py
arrow_bpmn/__spi__/action/continue_action.py
arrow_bpmn/__spi__/action/dequeue_action.py
arrow_bpmn/__spi__/action/event_action.py
arrow_bpmn/__spi__/action/incident_action.py
arrow_bpmn/__spi__/action/queue_action.py
arrow_bpmn/__spi__/action/resume_action.py
arrow_bpmn/__spi__/execution/__init__.py
arrow_bpmn/__spi__/execution/event_emitter.py
arrow_bpmn/__spi__/execution/executable.py
arrow_bpmn/__spi__/execution/execution_environment.py
