Metadata-Version: 2.1
Name: arrow.arrow-bpmn
Version: 0.1.17
Summary: Lightweight BPMN runtime.
Home-page: https://github.com/c7nw3r/arrow-bpmn
Author: x-and-y
Author-email: christian.weber@leftshift.one
License: Apache Software License
Download-URL: https://github.com/c7nw3r/arrow-bpmn/archive/refs/tags/v0.1.17.tar.gz
Keywords: bpmn-engine
Platform: UNKNOWN
Classifier: Development Status :: 4 - Beta
Classifier: Intended Audience :: Developers
Classifier: License :: OSI Approved :: Apache Software License
Classifier: Programming Language :: Python :: 3
Classifier: Programming Language :: Python :: 3.4
Classifier: Programming Language :: Python :: 3.5
Classifier: Programming Language :: Python :: 3.6
